markdown_del_ins.py
markdown_del_ins-1.0.0.dist-info/LICENSE
markdown_del_ins-1.0.0.dist-info/METADATA
markdown_del_ins-1.0.0.dist-info/WHEEL
markdown_del_ins-1.0.0.dist-info/top_level.txt
markdown_del_ins-1.0.0.dist-info/RECORD
