Metadata-Version: 2.1
Name: markdown-del-ins
Version: 1.0.0
Summary: Markdown extension to support the <del> and <ins> tags
Home-page: https://github.com/honzajavorek/markdown-del-ins
Author: Honza Javorek
Author-email: mail@honzajavorek.cz
License: UNKNOWN
Platform: UNKNOWN
Classifier: Operating System :: OS Independent
Classifier: License :: OSI Approved :: BSD License
Classifier: Intended Audience :: Developers
Classifier: Programming Language :: Python
Classifier: Topic :: Text Processing :: Filters
Classifier: Topic :: Text Processing :: Markup :: HTML
Requires-Dist: markdown (>=2.0)
